CHANGES.rst
LICENSE
MANIFEST.in
README.rst
requirements.txt
setup.cfg
setup.py
cloudberry_django_freeradius.egg-info/PKG-INFO
cloudberry_django_freeradius.egg-info/SOURCES.txt
cloudberry_django_freeradius.egg-info/dependency_links.txt
cloudberry_django_freeradius.egg-info/not-zip-safe
cloudberry_django_freeradius.egg-info/requires.txt
cloudberry_django_freeradius.egg-info/top_level.txt
django_freeradius/__init__.py
django_freeradius/admin.py
django_freeradius/apps.py
django_freeradius/models.py
django_freeradius/settings.py
django_freeradius/urls.py
django_freeradius/api/__init__.py
django_freeradius/api/serializers.py
django_freeradius/api/urls.py
django_freeradius/api/views.py
django_freeradius/base/__init__.py
django_freeradius/base/admin.py
django_freeradius/base/admin_actions.py
django_freeradius/base/admin_filters.py
django_freeradius/base/forms.py
django_freeradius/base/models.py
django_freeradius/management/__init__.py
django_freeradius/management/commands/__init__.py
django_freeradius/management/commands/cleanup_stale_radacct.py
django_freeradius/management/commands/delete_old_postauth.py
django_freeradius/management/commands/delete_old_radacct.py
django_freeradius/migrations/0001_initial.py
django_freeradius/migrations/0002_radiusaccounting_acct_update_time.py
django_freeradius/migrations/0003_auto_20170727_1613.py
django_freeradius/migrations/0004_auto_20170727_1635.py
django_freeradius/migrations/0005_radacct_fix_called_calling.py
django_freeradius/migrations/0006_postauth_improvements.py
django_freeradius/migrations/0007_nas_improvements.py
django_freeradius/migrations/0008_auto_20171004_1003.py
django_freeradius/migrations/0009_radiuscheck_expires.py
django_freeradius/migrations/0010_auto_20171107_1158.py
django_freeradius/migrations/0011_radiuscheck_note.py
django_freeradius/migrations/0012_auto_20171206_1546.py
django_freeradius/migrations/0013_auto_20171211_1045.py
django_freeradius/migrations/0014_auto_20171226_1938.py
django_freeradius/migrations/__init__.py
django_freeradius/static/django-freeradius/css/nas.css
django_freeradius/static/django-freeradius/css/radcheck.css
django_freeradius/static/django-freeradius/js/radcheck.js
django_freeradius/tests/__init__.py
django_freeradius/tests/test_admin.py
django_freeradius/tests/test_api.py
