Metadata-Version: 1.1
Name: cloudberry-django-freeradius
Version: 1234.0.1.0
Summary: Django reusable app that provides an admin interface to a freeradius database
Home-page: https://github.com/innovationgarage/django-freeradius
Author: Fiorella De Luca
Author-email: deluca_fiorella@yahoo.it
License: BSD
Download-URL: https://github.com/openwisp/django-freeradius/releases
Keywords: django,freeradius,radius,AAA,openwisp
Platform: Platform Indipendent
Classifier: Development Status :: 3 - Alpha
Classifier: Environment :: Web Environment
Classifier: Topic :: Internet :: WWW/HTTP
Classifier: Intended Audience :: Developers
Classifier: License :: OSI Approved :: BSD License
Classifier: Operating System :: OS Independent
Classifier: Framework :: Django
Classifier: Topic :: System :: Networking
Classifier: Programming Language :: Python :: 2.7
Classifier: Programming Language :: Python :: 3.4
